{
  "raceCode": "202605061605",
  "raceDate": "2026-05-06",
  "stadiumId": "16",
  "stadiumName": "児島",
  "raceNumber": 5,
  "raceName": "一般",
  "raceTitle": "第４２回鷲羽杯",
  "votingDeadline": "確定",
  "racers": [
    {
      "boatNumber": 1,
      "registrationNumber": 3746,
      "racerName": "岡瀬 正人",
      "classGrade": "A2",
      "age": 51,
      "branch": "岡山",
      "nationalAvgST": 0.17,
      "nationalWinRate": 5.57,
      "nationalTop2Rate": 35.7,
      "localWinRate": 5.95,
      "localTop2Rate": 42.5,
      "motorNumber": 64,
      "motorTop2Rate": 26.4
    },
    {
      "boatNumber": 2,
      "registrationNumber": 5037,
      "racerName": "田頭 虎親",
      "classGrade": "B1",
      "age": 28,
      "branch": "香川",
      "nationalAvgST": 0.19,
      "nationalWinRate": 5.49,
      "nationalTop2Rate": 39,
      "localWinRate": 5.36,
      "localTop2Rate": 38.1,
      "motorNumber": 54,
      "motorTop2Rate": 33.9
    },
    {
      "boatNumber": 3,
      "registrationNumber": 3822,
      "racerName": "平尾 崇典",
      "classGrade": "A1",
      "age": 53,
      "branch": "岡山",
      "nationalAvgST": 0.16,
      "nationalWinRate": 6.68,
      "nationalTop2Rate": 44.3,
      "localWinRate": 6.97,
      "localTop2Rate": 52.7,
      "motorNumber": 69,
      "motorTop2Rate": 30.6
    },
    {
      "boatNumber": 4,
      "registrationNumber": 4277,
      "racerName": "金田 大輔",
      "classGrade": "B1",
      "age": 42,
      "branch": "岡山",
      "nationalAvgST": 0.15,
      "nationalWinRate": 5.09,
      "nationalTop2Rate": 37.6,
      "localWinRate": 4.71,
      "localTop2Rate": 24.4,
      "motorNumber": 19,
      "motorTop2Rate": 30.2
    },
    {
      "boatNumber": 5,
      "registrationNumber": 4214,
      "racerName": "林 祐介",
      "classGrade": "A2",
      "age": 41,
      "branch": "岡山",
      "nationalAvgST": 0.17,
      "nationalWinRate": 5.29,
      "nationalTop2Rate": 33.3,
      "localWinRate": 5.58,
      "localTop2Rate": 34.2,
      "motorNumber": 55,
      "motorTop2Rate": 46
    },
    {
      "boatNumber": 6,
      "registrationNumber": 5111,
      "racerName": "三村 岳人",
      "classGrade": "B2",
      "age": 26,
      "branch": "岡山",
      "nationalAvgST": 0.19,
      "nationalWinRate": 5.97,
      "nationalTop2Rate": 45.3,
      "localWinRate": 5.49,
      "localTop2Rate": 32.7,
      "motorNumber": 31,
      "motorTop2Rate": 39
    }
  ],
  "startPrediction": {
    "fromExhibition": true,
    "entries": [
      {
        "boatNumber": 1,
        "courseNumber": 1,
        "startTiming": 0.17
      },
      {
        "boatNumber": 2,
        "courseNumber": 2,
        "startTiming": 0.19
      },
      {
        "boatNumber": 3,
        "courseNumber": 3,
        "startTiming": 0.16
      },
      {
        "boatNumber": 4,
        "courseNumber": 4,
        "startTiming": 0.15
      },
      {
        "boatNumber": 5,
        "courseNumber": 5,
        "startTiming": 0.17
      },
      {
        "boatNumber": 6,
        "courseNumber": 6,
        "startTiming": 0.19
      }
    ]
  },
  "aiEvaluation": {
    "state": "realtime",
    "entries": [
      {
        "boatNumber": 1,
        "contribution": {
          "frame": 31.27,
          "racer": 11.05,
          "motor": 7.41,
          "exhibition": 5.92,
          "weather": 2.89
        },
        "strengthPt": 58.54
      },
      {
        "boatNumber": 2,
        "contribution": {
          "frame": 23.11,
          "racer": 10.12,
          "motor": 9.02,
          "exhibition": 4.62,
          "weather": 2.92
        },
        "strengthPt": 49.79
      },
      {
        "boatNumber": 3,
        "contribution": {
          "frame": 23.09,
          "racer": 13.36,
          "motor": 9.52,
          "exhibition": 5.45,
          "weather": 2.65
        },
        "strengthPt": 54.08
      },
      {
        "boatNumber": 4,
        "contribution": {
          "frame": 22.83,
          "racer": 10.12,
          "motor": 11.27,
          "exhibition": 4.93,
          "weather": 2.28
        },
        "strengthPt": 51.43
      },
      {
        "boatNumber": 5,
        "contribution": {
          "frame": 18.66,
          "racer": 10.12,
          "motor": 8.54,
          "exhibition": 5.62,
          "weather": 3.49
        },
        "strengthPt": 46.44
      },
      {
        "boatNumber": 6,
        "contribution": {
          "frame": 16.1,
          "racer": 11.05,
          "motor": 10.3,
          "exhibition": 4.71,
          "weather": 3.06
        },
        "strengthPt": 45.21
      }
    ]
  },
  "generatedAt": "2026-05-06T04:52:34.635Z"
}