{
  "raceCode": "202605061002",
  "raceDate": "2026-05-06",
  "stadiumId": "10",
  "stadiumName": "三国",
  "raceNumber": 2,
  "raceName": "みくにあさガ",
  "raceTitle": "ＧＷ三国ボートフェスタ",
  "votingDeadline": "09:14",
  "racers": [
    {
      "boatNumber": 1,
      "registrationNumber": 4298,
      "racerName": "宮下 元胤",
      "classGrade": "A1",
      "age": 43,
      "branch": "愛知",
      "nationalAvgST": 0.17,
      "nationalWinRate": 6.23,
      "nationalTop2Rate": 46.3,
      "localWinRate": 6.24,
      "localTop2Rate": 52.3,
      "motorNumber": 60,
      "motorTop2Rate": 38.8
    },
    {
      "boatNumber": 2,
      "registrationNumber": 5038,
      "racerName": "金田 智博",
      "classGrade": "A2",
      "age": 28,
      "branch": "福井",
      "nationalAvgST": 0.17,
      "nationalWinRate": 6.33,
      "nationalTop2Rate": 48.4,
      "localWinRate": 6.16,
      "localTop2Rate": 46.6,
      "motorNumber": 55,
      "motorTop2Rate": 38.4
    },
    {
      "boatNumber": 3,
      "registrationNumber": 4139,
      "racerName": "丹下 健",
      "classGrade": "B1",
      "age": 45,
      "branch": "愛知",
      "nationalAvgST": 0.17,
      "nationalWinRate": 4.29,
      "nationalTop2Rate": 26,
      "localWinRate": 4.81,
      "localTop2Rate": 34.6,
      "motorNumber": 36,
      "motorTop2Rate": 24.2
    },
    {
      "boatNumber": 4,
      "registrationNumber": 4692,
      "racerName": "酒井 俊弘",
      "classGrade": "B1",
      "age": 42,
      "branch": "福井",
      "nationalAvgST": 0.15,
      "nationalWinRate": 5.15,
      "nationalTop2Rate": 37.2,
      "localWinRate": 4.81,
      "localTop2Rate": 33.9,
      "motorNumber": 42,
      "motorTop2Rate": 45.1
    },
    {
      "boatNumber": 5,
      "registrationNumber": 4666,
      "racerName": "日笠 勝弘",
      "classGrade": "B2",
      "age": 42,
      "branch": "大阪",
      "nationalAvgST": 0.16,
      "nationalWinRate": 4.14,
      "nationalTop2Rate": 20,
      "localWinRate": 4.5,
      "localTop2Rate": 31.2,
      "motorNumber": 12,
      "motorTop2Rate": 41.3
    },
    {
      "boatNumber": 6,
      "registrationNumber": 3620,
      "racerName": "信濃 由行",
      "classGrade": "B1",
      "age": 52,
      "branch": "福井",
      "nationalAvgST": 0.17,
      "nationalWinRate": 4.13,
      "nationalTop2Rate": 24,
      "localWinRate": 4.1,
      "localTop2Rate": 20.5,
      "motorNumber": 19,
      "motorTop2Rate": 32.1
    }
  ],
  "startPrediction": {
    "fromExhibition": true,
    "entries": [
      {
        "boatNumber": 1,
        "courseNumber": 1,
        "startTiming": 0.17
      },
      {
        "boatNumber": 2,
        "courseNumber": 2,
        "startTiming": 0.17
      },
      {
        "boatNumber": 3,
        "courseNumber": 3,
        "startTiming": 0.17
      },
      {
        "boatNumber": 5,
        "courseNumber": 4,
        "startTiming": 0.16
      },
      {
        "boatNumber": 6,
        "courseNumber": 5,
        "startTiming": 0.17
      },
      {
        "boatNumber": 4,
        "courseNumber": 6,
        "startTiming": 0.15
      }
    ]
  },
  "aiEvaluation": {
    "state": "realtime",
    "entries": [
      {
        "boatNumber": 1,
        "contribution": {
          "frame": 26.84,
          "racer": 13.8,
          "motor": 19.91,
          "exhibition": 6.08,
          "weather": 1.87
        },
        "strengthPt": 68.51
      },
      {
        "boatNumber": 2,
        "contribution": {
          "frame": 21.32,
          "racer": 13.8,
          "motor": 16.56,
          "exhibition": 7.92,
          "weather": 2.21
        },
        "strengthPt": 61.8
      },
      {
        "boatNumber": 3,
        "contribution": {
          "frame": 20.53,
          "racer": 13.8,
          "motor": 16.94,
          "exhibition": 7,
          "weather": 2.09
        },
        "strengthPt": 60.36
      },
      {
        "boatNumber": 4,
        "contribution": {
          "frame": 13.43,
          "racer": 13.8,
          "motor": 19.74,
          "exhibition": 5.72,
          "weather": 2.26
        },
        "strengthPt": 54.95
      },
      {
        "boatNumber": 5,
        "contribution": {
          "frame": 19.23,
          "racer": 13.8,
          "motor": 17.18,
          "exhibition": 5.03,
          "weather": 1.99
        },
        "strengthPt": 57.23
      },
      {
        "boatNumber": 6,
        "contribution": {
          "frame": 16.56,
          "racer": 13.8,
          "motor": 18.8,
          "exhibition": 4.6,
          "weather": 2.15
        },
        "strengthPt": 55.92
      }
    ]
  },
  "generatedAt": "2026-05-06T04:18:37.549Z"
}