{
  "raceCode": "202605062005",
  "raceDate": "2026-05-06",
  "stadiumId": "20",
  "stadiumName": "若松",
  "raceNumber": 5,
  "raceName": "進入固定戦隊 進入固定 Ｈ１８０",
  "raceTitle": "スポーツニッポン杯ＧＷ特選競走",
  "votingDeadline": "16:58",
  "racers": [
    {
      "boatNumber": 1,
      "registrationNumber": 3898,
      "racerName": "平田 忠則",
      "classGrade": "A1",
      "age": 49,
      "branch": "福岡",
      "nationalAvgST": 0.14,
      "nationalWinRate": 7,
      "nationalTop2Rate": 52.1,
      "localWinRate": 6.53,
      "localTop2Rate": 48.3,
      "motorNumber": 45,
      "motorTop2Rate": 36.2
    },
    {
      "boatNumber": 2,
      "registrationNumber": 4607,
      "racerName": "鶴田 勇雄",
      "classGrade": "A2",
      "age": 37,
      "branch": "福岡",
      "nationalAvgST": 0.18,
      "nationalWinRate": 5.42,
      "nationalTop2Rate": 29,
      "localWinRate": 6.05,
      "localTop2Rate": 35,
      "motorNumber": 43,
      "motorTop2Rate": 32.6
    },
    {
      "boatNumber": 3,
      "registrationNumber": 5207,
      "racerName": "高山 敬悟",
      "classGrade": "B1",
      "age": 28,
      "branch": "福岡",
      "nationalAvgST": 0.15,
      "nationalWinRate": 4.77,
      "nationalTop2Rate": 29.5,
      "localWinRate": 4.21,
      "localTop2Rate": 29.7,
      "motorNumber": 54,
      "motorTop2Rate": 33.3
    },
    {
      "boatNumber": 4,
      "registrationNumber": 4403,
      "racerName": "木下 大將",
      "classGrade": "A2",
      "age": 41,
      "branch": "福岡",
      "nationalAvgST": 0.16,
      "nationalWinRate": 5.97,
      "nationalTop2Rate": 44.5,
      "localWinRate": 6.56,
      "localTop2Rate": 50,
      "motorNumber": 42,
      "motorTop2Rate": 38.3
    },
    {
      "boatNumber": 5,
      "registrationNumber": 5071,
      "racerName": "野見山 拓己",
      "classGrade": "B1",
      "age": 31,
      "branch": "福岡",
      "nationalAvgST": 0.12,
      "nationalWinRate": 4.96,
      "nationalTop2Rate": 26.9,
      "localWinRate": 4.53,
      "localTop2Rate": 23.5,
      "motorNumber": 31,
      "motorTop2Rate": 36.5
    },
    {
      "boatNumber": 6,
      "registrationNumber": 5022,
      "racerName": "伊藤 尚汰",
      "classGrade": "B1",
      "age": 31,
      "branch": "福岡",
      "nationalAvgST": 0.16,
      "nationalWinRate": 4,
      "nationalTop2Rate": 20.6,
      "localWinRate": 4.68,
      "localTop2Rate": 27.2,
      "motorNumber": 34,
      "motorTop2Rate": 38.4
    }
  ],
  "startPrediction": {
    "fromExhibition": false,
    "entries": [
      {
        "boatNumber": 1,
        "courseNumber": 1,
        "startTiming": 0.14
      },
      {
        "boatNumber": 2,
        "courseNumber": 2,
        "startTiming": 0.18
      },
      {
        "boatNumber": 3,
        "courseNumber": 3,
        "startTiming": 0.15
      },
      {
        "boatNumber": 4,
        "courseNumber": 4,
        "startTiming": 0.16
      },
      {
        "boatNumber": 5,
        "courseNumber": 5,
        "startTiming": 0.12
      },
      {
        "boatNumber": 6,
        "courseNumber": 6,
        "startTiming": 0.16
      }
    ]
  },
  "aiEvaluation": {
    "state": "daily",
    "entries": [
      {
        "boatNumber": 1,
        "contribution": {
          "frame": 29.96,
          "racer": 11,
          "motor": 6.58,
          "exhibition": 0,
          "weather": 0
        },
        "strengthPt": 57.89
      },
      {
        "boatNumber": 2,
        "contribution": {
          "frame": 22.83,
          "racer": 11,
          "motor": 4.26,
          "exhibition": 0,
          "weather": 0
        },
        "strengthPt": 48.44
      },
      {
        "boatNumber": 3,
        "contribution": {
          "frame": 22.34,
          "racer": 11,
          "motor": 7.99,
          "exhibition": 0,
          "weather": 0
        },
        "strengthPt": 51.68
      },
      {
        "boatNumber": 4,
        "contribution": {
          "frame": 21.44,
          "racer": 11,
          "motor": 8.69,
          "exhibition": 0,
          "weather": 0
        },
        "strengthPt": 51.48
      },
      {
        "boatNumber": 5,
        "contribution": {
          "frame": 19.16,
          "racer": 11,
          "motor": 5.34,
          "exhibition": 0,
          "weather": 0
        },
        "strengthPt": 45.85
      },
      {
        "boatNumber": 6,
        "contribution": {
          "frame": 16.53,
          "racer": 11,
          "motor": 7.02,
          "exhibition": 0,
          "weather": 0
        },
        "strengthPt": 44.91
      }
    ]
  },
  "generatedAt": "2026-05-06T04:18:37.549Z"
}